setup.py
netgen/__init__.py
netgen/engine.py
netgen/main.py
netgen/test.py
netgen.egg-info/PKG-INFO
netgen.egg-info/SOURCES.txt
netgen.egg-info/dependency_links.txt
netgen.egg-info/entry_points.txt
netgen.egg-info/requires.txt
netgen.egg-info/top_level.txt