Metadata-Version: 1.1
Name: netgen
Version: 0.2.0
Summary: a templated ip address plan generator
Home-page: https://github.com/nlm/netgen
Author: Nicolas Limage
Author-email: UNKNOWN
License: GPL
Keywords: ip range network space
Platform: UNKNOWN
Classifier: Development Status :: 4 - Beta
Classifier: Environment :: Console
Classifier: Intended Audience :: System Administrators
Classifier: License :: OSI Approved :: GNU General Public License (GPL)
Classifier: Operating System :: OS Independent
Classifier: Programming Language :: Python
Classifier: Topic :: System :: Networking
